nexpose_rest/__init__.py
nexpose_rest/nexpose.py
nexpose_rest/nexpose_administration.py
nexpose_rest/nexpose_asset.py
nexpose_rest/nexpose_asset_discovery.py
nexpose_rest/nexpose_asset_group.py
nexpose_rest/nexpose_credential.py
nexpose_rest/nexpose_policy.py
nexpose_rest/nexpose_policy_override.py
nexpose_rest/nexpose_remediation.py
nexpose_rest/nexpose_report.py
nexpose_rest/nexpose_root.py
nexpose_rest/nexpose_scan.py
nexpose_rest/nexpose_scan_engine.py
nexpose_rest/nexpose_scan_template.py
nexpose_rest/nexpose_site.py
nexpose_rest/nexpose_tag.py
nexpose_rest/nexpose_user.py
nexpose_rest/nexpose_vulnerability.py
nexpose_rest/nexpose_vulnerability_check.py
nexpose_rest/nexpose_vulnerability_exception.py
nexpose_rest/nexpose_vulnerability_result.py
nexpose_rest-0.2.dist-info/DESCRIPTION.rst
nexpose_rest-0.2.dist-info/METADATA
nexpose_rest-0.2.dist-info/RECORD
nexpose_rest-0.2.dist-info/WHEEL
nexpose_rest-0.2.dist-info/metadata.json
nexpose_rest-0.2.dist-info/top_level.txt
