Metadata-Version: 2.0
Name: nexpose-rest
Version: 0.2
Summary: Basic inofficial implementation of the nexpose rest api
Home-page: https://github.com/Patralos/nexpose-rest/
Author: Patrick Pirker
Author-email: pypi@patralos.at
License: UNKNOWN
Platform: UNKNOWN
Classifier: Programming Language :: Python :: 3
Classifier: License :: OSI Approved :: MIT License
Classifier: Operating System :: OS Independent
